nnez/__init__.py
nnez/core.py
nnez/grammar.py
nnez/py.typed
nnez-0.1.3.dist-info/licenses/LICENSE
nnez-0.1.3.dist-info/METADATA
nnez-0.1.3.dist-info/WHEEL
nnez-0.1.3.dist-info/top_level.txt
nnez-0.1.3.dist-info/RECORD
