Metadata-Version: 2.4
Name: nnez
Version: 0.1.3
Summary: Neural Network Easy Extraction - Simple LLM activation extraction in one line
Home-page: https://github.com/yourusername/nnez
Author: Your Name
Author-email: Paul Bogdan <paulcbogdan@gmail.com>
License: MIT
Project-URL: Homepage, https://github.com/yourusername/nnez
Project-URL: Documentation, https://nnez.readthedocs.io/
Project-URL: Repository, https://github.com/yourusername/nnez.git
Project-URL: Bug Tracker, https://github.com/yourusername/nnez/issues
Project-URL: Changelog, https://github.com/yourusername/nnez/blob/main/CHANGELOG.md
Keywords: llm,transformers,activation-extraction,interpretability,neural-networks,nlp,machine-learning,deep-learning,gpt,bert,probing,residual-stream
Classifier: Development Status :: 4 - Beta
Classifier: Intended Audience :: Developers
Classifier: Intended Audience :: Science/Research
Classifier: License :: OSI Approved :: MIT License
Classifier: Operating System :: OS Independent
Classifier: Programming Language :: Python :: 3
Classifier: Programming Language :: Python :: 3.8
Classifier: Programming Language :: Python :: 3.9
Classifier: Programming Language :: Python :: 3.10
Classifier: Programming Language :: Python :: 3.11
Classifier: Programming Language :: Python :: 3.12
Classifier: Topic :: Scientific/Engineering :: Artificial Intelligence
Classifier: Topic :: Software Development :: Libraries :: Python Modules
Requires-Python: >=3.8
License-File: LICENSE
Requires-Dist: torch>=1.9.0
Requires-Dist: transformers>=4.20.0
Requires-Dist: nnsight>=0.2.0
Requires-Dist: numpy>=1.19.0
Requires-Dist: inflect>=6.0.0
Requires-Dist: typing-extensions>=4.0.0
Provides-Extra: dev
Requires-Dist: pytest>=7.0.0; extra == "dev"
Requires-Dist: pytest-cov>=4.0.0; extra == "dev"
Requires-Dist: black>=22.0.0; extra == "dev"
Requires-Dist: isort>=5.10.0; extra == "dev"
Requires-Dist: flake8>=4.0.0; extra == "dev"
Requires-Dist: mypy>=0.950; extra == "dev"
Requires-Dist: pre-commit>=2.17.0; extra == "dev"
Provides-Extra: docs
Requires-Dist: sphinx>=4.5.0; extra == "docs"
Requires-Dist: sphinx-rtd-theme>=1.0.0; extra == "docs"
Requires-Dist: sphinx-autodoc-typehints>=1.18.0; extra == "docs"
Provides-Extra: examples
Requires-Dist: scipy>=1.7.0; extra == "examples"
Requires-Dist: matplotlib>=3.4.0; extra == "examples"
Requires-Dist: seaborn>=0.11.0; extra == "examples"
Requires-Dist: jupyter>=1.0.0; extra == "examples"
Requires-Dist: ipywidgets>=7.6.0; extra == "examples"
Dynamic: author
Dynamic: home-page
Dynamic: license-file
Dynamic: requires-python
